seethrufeeds/__init__.py
seethrufeeds/core/__init__.py
seethrufeeds/core/config_parser.py
seethrufeeds/core/seethru_feed.py
seethrufeeds/core/config/__init__.py
seethrufeeds/core/config/apikey.py
seethrufeeds/core/config/feed.py
seethrufeeds/core/config/header.py
seethrufeeds/core/config/script/__init__.py
seethrufeeds/core/config/script/meta.py
seethrufeeds/core/config/script/state.py
seethrufeeds/core/exceptions/__init__.py
seethrufeeds/core/exceptions/config.py
seethrufeeds/feeds/__init__.py
seethrufeeds/feeds/api_key.py
seethrufeeds/feeds/exceptions.py
seethrufeeds/feeds/feed.py
seethrufeeds/feeds/feed_result.py
seethrufeeds/library/__init__.py
seethrufeeds/library/components/__init__.py
seethrufeeds/library/components/database.py
seethrufeeds/library/components/http.py
seethrufeeds/library/components/snmp.py
seethrufeeds/library/components/socket.py
seethrufeeds/library/components/zabbix.py
seethrufeeds/library/scripts/__init__.py
seethrufeeds/library/scripts/status_page.py
seethrufeeds/library/scripts/tcp_port_open.py
seethrufeeds/library/scripts/udp_port_open.py
seethrufeeds/model/__init__.py
seethrufeeds/model/attribution.py
seethrufeeds/model/components/__init__.py
seethrufeeds/model/components/component_base.py
seethrufeeds/model/scripts/__init__.py
seethrufeeds/model/scripts/script_base.py
seethrufeeds/model/scripts/script_state.py
tests/__init__.py
tests/scripts.py
tests/test_Core_ConfigParser.py
tests/test_SeeThru_Feed.py
tests/feeds/__init__.py
tests/feeds/test_api_key.py
tests/feeds/test_feed_result.py
seethrufeeds-0.1.4.dist-info/LICENSE
seethrufeeds-0.1.4.dist-info/METADATA
seethrufeeds-0.1.4.dist-info/WHEEL
seethrufeeds-0.1.4.dist-info/entry_points.txt
seethrufeeds-0.1.4.dist-info/top_level.txt
seethrufeeds-0.1.4.dist-info/RECORD
