Metadata-Version: 2.1
Name: seethrufeeds
Version: 0.1.4
Summary: The SeeThruNetworks feed framework
Home-page: https://github.com/SeeThru-Networks/Python-Feeds
Author: SeeThru Networks
Author-email: aidan@seethrunetworks.com
License: MIT
Project-URL: Website, https://www.seethrunetworks.com/
Keywords: seethru,seethrunetworks,feed
Platform: UNKNOWN
Classifier: Intended Audience :: Developers
Classifier: License :: OSI Approved :: MIT License
Classifier: Operating System :: OS Independent
Classifier: Programming Language :: Python
Classifier: Programming Language :: Python :: 3
Classifier: Programming Language :: Python :: 3 :: Only
Requires-Python: >=3.9
Requires-Dist: requests
Requires-Dist: python-dotenv
Requires-Dist: toml
Requires-Dist: mysql-connector-python
Requires-Dist: py-zabbix
Requires-Dist: pydantic
